pollination/two_phase_daylight_coefficient/__init__.py
pollination/two_phase_daylight_coefficient/_prepare_folder.py
pollination/two_phase_daylight_coefficient/entry.py
pollination/two_phase_daylight_coefficient/two_phase/__init__.py
pollination/two_phase_daylight_coefficient/two_phase/_raytracing.py
pollination/two_phase_daylight_coefficient/two_phase/entry.py
pollination_two_phase_daylight_coefficient-1.1.59.dist-info/LICENSE
pollination_two_phase_daylight_coefficient-1.1.59.dist-info/METADATA
pollination_two_phase_daylight_coefficient-1.1.59.dist-info/WHEEL
pollination_two_phase_daylight_coefficient-1.1.59.dist-info/top_level.txt
pollination_two_phase_daylight_coefficient-1.1.59.dist-info/RECORD
