Metadata-Version: 2.1
Name: pollination-two-phase-daylight-coefficient
Version: 1.1.59
Summary: Two phase daylight coefficient recipe for Pollination.
Home-page: https://github.com/pollination/two-phase-daylight-coefficient
Author: ladybug-tools
Author-email: info@ladybug.tools
Maintainer: mikkel, ladybug-tools
Maintainer-email: mikkel@ladybug.tools, info@ladybug.tools
License: PolyForm Shield License 1.0.0, https://polyformproject.org/wp-content/uploads/2020/06/PolyForm-Shield-1.0.0.txt
Project-URL: icon, https://raw.githubusercontent.com/ladybug-tools/artwork/master/icons_components/honeybee/png/annualrecipe.png
Project-URL: docker, https://hub.docker.com/r/ladybugtools/honeybee-radiance
Keywords: honeybee,radiance,ladybug-tools,daylight,annual-daylight
License-File: LICENSE
Requires-Dist: pollination-honeybee-radiance>=0.22.68
Requires-Dist: pollination-honeybee-radiance-postprocess>=0.0.94
Requires-Dist: pollination-alias>=0.11.15
Requires-Dist: pollination-path>=0.3.4
